README.rst
setup.py
aquaipy/__init__.py
aquaipy/aquaipy.py
aquaipy/error.py
aquaipy.egg-info/PKG-INFO
aquaipy.egg-info/SOURCES.txt
aquaipy.egg-info/dependency_links.txt
aquaipy.egg-info/requires.txt
aquaipy.egg-info/top_level.txt