Metadata-Version: 2.1
Name: aquaipy
Version: 2.0.1
Summary: Python library for controlling the AquaIllumination range of aquarium lights
Home-page: http://github.com/mcclown/AquaIPy/
Author: Stephen Mc Gowan
Author-email: mcclown@gmail.com
License: Apache Software License
Platform: any
Classifier: Programming Language :: Python
Classifier: Development Status :: 4 - Beta
Classifier: Natural Language :: English
Classifier: Environment :: Web Environment
Classifier: Intended Audience :: Developers
Classifier: License :: OSI Approved :: Apache Software License
Classifier: Operating System :: OS Independent
Classifier: Topic :: Software Development :: Libraries :: Python Modules
Classifier: Topic :: Software Development :: Libraries :: Application Frameworks
Provides-Extra: testing
